[
    {
        "label":"Zoo",
        "value":"zoo"
    },
    {   "label":"Pet Groomer",
        "value":"pet_groomer"
    },
     {   "label":"Pet Breeder",
        "value":"pet_breeder"
    },
     {   "label":"Pet Adoption",
        "value":"pet_adoption"
    },
    {
       "label":"Pet Waste Removal",
        "value":"pet_waste_removal"
    },
      {   "label":"Pet Sitting",
        "value":"pet_sitting"
    },
     {   "label":"Pet Transportation",
        "value":"pet_transportation"
    },
    {
       "label":"Pet Photography",
        "value":"pet_photography"
    },
     {
       "label":"Holistic Animal Care",
        "value":"holistic_animal_care"
    },
     {
       "label":"Veterinarian",
        "value":"veterinarian"
    },
     {
       "label":"Amusement Park",
        "value":"amusement_park"
    },
    {
       "label":"Aquarium",
        "value":"aquarium"
    },
     {
       "label":"Art Gallery",
        "value":"art_gallery"
    },
     {
       "label":"Beach",
        "value":"beach"
    },
      {
       "label":"Boat Rental And Training",
        "value":"boat_rental_and_training"
    },
    {
       "label":"Haunted House",
        "value":"haunted_house"
    },
    {
       "label":"Horseback Riding Service",
        "value":"horseback_riding_service"
    },
     {
       "label":"Hot Air Ballon Tours",
        "value":"hot_air_balloons_tour"
    },
    {
       "label":"Marina",
        "value":"marina"
    },
      {
       "label":"Observatory",
        "value":"observatory"
    },
     {
       "label":"Rock Climbing Spot",
        "value":"rock_climbing_spot"
    },
    {
       "label":"Ski Area",
        "value":"ski_area"
    },
      {
       "label":"Snorkeling",
        "value":"snorkeling"
    },
     {
       "label":"Snowboarding Center",
        "value":"snowboarding_center"
    },
      {
       "label":"Street Art",
        "value":"street_art"
    },
    {
       "label":"Waterfall",
        "value":"waterfall"
    },
    {
       "label":"Surfing",
        "value":"surfing"
    },
    {
       "label":"Petting Zoo",
        "value":"petting_zoo"
    }
]

